ezmsg/xdf/__init__.py
ezmsg/xdf/__version__.py
ezmsg/xdf/iter.py
ezmsg/xdf/source.py
ezmsg_xdf-0.4.0.dist-info/METADATA
ezmsg_xdf-0.4.0.dist-info/WHEEL
ezmsg_xdf-0.4.0.dist-info/licenses/LICENSE
ezmsg_xdf-0.4.0.dist-info/RECORD
